{"name":"Infinitydisplay","tagline":"","body":"# The Infinity Display\r\n\r\n<img src=\"infdis.jpg\" width=\"500px\"/>\r\n\r\n## Overview\r\n\r\nThis is a web application that collects parameter values for a LED display.\r\n\r\nThe current version will ask a user for four values:\r\n\r\n  * Equalizer opacity\r\n  * Wave form opacity\r\n  * Sound reactive sensitivity\r\n  * Trail effect intensity\r\n\r\n<img src=\"submitpage.JPG\" width=\"500px\"/>\r\n\r\nThese values are then packaged into a text file that is then read by the device driving the LEDs.\r\n\r\nTo use this, the user must have both IntelliJ and Processing installed.\r\n\r\nA physical LED display is not required to develop code for this project.\r\n\r\nAnimations can be simulated using a Processing GUI.\r\n\r\n## Features\r\n\r\nThe Infinity Display provides the following features:\r\n\r\n  * Visual and interactive stimulation\r\n  * Communication between two programs\r\n  * Remote access\r\n  * Blindness\r\n\r\n## Version information\r\n\r\nPlay 2.3.7, Bootstrap 3.3.2\r\n\r\n","google":"","note":"Don't delete this file! It's used internally to help with page regeneration."}